{"batchcomplete": "", "query": {"pages": {"6586020": {"ns": 0, "pageid": 6586020, "revisions": [{"*": "'''Colin \"Col\" Hutchinson''' is a veteran [[statistician]], most notably in the [[VFL/AFL|Victorian/Australian Football League]] in the sport of [[Australian rules football]]. He was the AFL's official historian from the 1990s<ref>[http://www.theage.com.au/articles/2004/02/19/1077072783487.html?from=storyrhs Sporting Life – Sport – www.theage.com.au]</ref> until around 2005.\n\nA part of the [[AFLPA]], Hutchinson provides interesting statistics on football to newspapers and media outlets.\n\nHe is the author of several books including a history of the [[Geelong Football Club]] (''Cats' tales : the Geelong Football Club, 1897–1983'')<ref>''Cats' tales : the Geelong Football Club, 1897–1983''. Geelong Advertiser, 1984</ref> and ''The AFL footy quiz book''.<ref>{{cite book| author = Col Hutchinson| title = The AFL Footy Quiz Book| url = http://books.google.com/?id=xl23AAAACAAJ| date = 2002| publisher = Penguin Group Australia| isbn = 978-0-14-300036-5 }}</ref>\n\nThe last time Hutchinson missed seeing a live Geelong Football Club game was in 1963, over 1,100 games ago.<ref>[http://www.smh.com.au/afl/afl-news/1100-games-and-counting-20110826-1jel1.html 1100 games and counting]</ref>\n\n==References==\n{{reflist}}\n\n\n{{Persondata <!-- Metadata: see [[Wikipedia:Persondata]]. --> \n| NAME              = Hutchinson, Col\n| ALTERNATIVE NAMES =\n| SHORT DESCRIPTION = Australian rules football statistician\n| DATE OF BIRTH     =\n| PLACE OF BIRTH    =\n| DATE OF DEATH     =\n| PLACE OF DEATH    =\n}}\n{{DEFAULTSORT:Hutchinson, Col}}\n[[Category:Australian statisticians]]\n[[Category:Australian historians]]\n[[Category:Year of birth missing (living people)]]\n[[Category:Living people]]\n\n\n{{AFL-bio-stub}}\n{{Australia-scientist-stub}}\n{{statistician-stub}}", "contentmodel": "wikitext", "contentformat": "text/x-wiki"}], "title": "Col Hutchinson"}}}}